data_generation/__init__.py
data_generation/code_gen.py
data_generation/generator_custom.py
data_generation/code_generator/__init__.py
data_generation/code_generator/config/__init__.py
data_generation/code_generator/config/arguments.json
data_generation/code_generator/helpers/__init__.py
data_generation/code_generator/helpers/generator_helper.py
data_generation/code_generator/helpers/save_batches.py
data_generation/code_generator/helpers/seed_helper.py
data_generation/code_generator/languages/__init__.py
data_generation/code_generator/languages/languages_class.py
data_generation/code_generator/prompts/__init__.py
data_generation/code_generator/prompts/complex_brief_prompt.py
data_generation/code_generator/prompts/complex_conversational_prompt.py
data_generation/code_generator/prompts/complex_prompt.py
data_generation/code_generator/prompts/prompt.py
data_generation/code_generator/prompts/prompt_list_and_probabilities.py
data_generation/code_generator/utils/__init__.py
data_generation/code_generator/utils/util.py
data_generation_hyper-0.0.5.4.dist-info/METADATA
data_generation_hyper-0.0.5.4.dist-info/WHEEL
data_generation_hyper-0.0.5.4.dist-info/top_level.txt
data_generation_hyper-0.0.5.4.dist-info/RECORD
