Metadata-Version: 2.1
Name: data-generation-hyper
Version: 0.0.5.4
Summary: Library for synthetic data generation
Home-page: https://github.com/cesbid/data_generation
Author: Cesare Bidini, Onuralp Guvercin, Emin Yuksel, Mevlut
Author-email: cesare.bidini@gmail.com
Classifier: Programming Language :: Python :: 3
Classifier: License :: OSI Approved :: MIT License
Classifier: Operating System :: OS Independent
